slabdip/__init__.py
slabdip/predictor.py
slabdip/data/subduction_data.csv
slabdip-4.2.2.dist-info/LICENSE
slabdip-4.2.2.dist-info/METADATA
slabdip-4.2.2.dist-info/WHEEL
slabdip-4.2.2.dist-info/top_level.txt
slabdip-4.2.2.dist-info/RECORD
