Metadata-Version: 2.2
Name: slabdip
Version: 4.2.2
Summary: Method to calculate slab dip using simple plate kinematic parameters
Home-page: https://github.com/brmather/Slab-Dip
Author: Ben Mather
Author-email: ben.mather@sydney.edu.au
Classifier: Programming Language :: Python :: 2
Classifier: Programming Language :: Python :: 2.6
Classifier: Programming Language :: Python :: 2.7
Classifier: Programming Language :: Python :: 3
Classifier: Programming Language :: Python :: 3.3
Classifier: Programming Language :: Python :: 3.4
Classifier: Programming Language :: Python :: 3.5
Classifier: Programming Language :: Python :: 3.6
Classifier: Programming Language :: Python :: 3.7
Classifier: Programming Language :: Python :: 3.8
Classifier: Programming Language :: Python :: 3.9
Classifier: Programming Language :: Python :: 3.10
Classifier: Programming Language :: Python :: 3.11
Classifier: Programming Language :: Python :: 3.12
License-File: LICENSE
Requires-Dist: pandas
Requires-Dist: numpy
Requires-Dist: scikit-learn
Requires-Dist: gplately>=1.0
Provides-Extra: plotting
Requires-Dist: matplotlib; extra == "plotting"
Requires-Dist: jupyter; extra == "plotting"
Requires-Dist: cartopy; extra == "plotting"
Dynamic: author
Dynamic: author-email
Dynamic: classifier
Dynamic: description
Dynamic: description-content-type
Dynamic: home-page
Dynamic: provides-extra
Dynamic: requires-dist
Dynamic: summary
